Experiment 5- Pipelining/Wallace.v
module WalMul(input [15:0] M,input [15:0] N,output [31:0] O,input clk);

wire [15:0] M,N;
wire [31:0] O;
wire [31:0] a1,a2,a3,a4,a5,a6,a7,a8,a9,a10,a11,a12,a13,a14,a15,a16;
reg [31:0] b1,b2,b3,b4,b5,b55,b6,b7,b8,b9,b10,b11,b12,b13,b14,a161,a162,a163;
reg [31:0] o1,o2,o3,o4,o5,o6,o7,o8,o9,o10,o11,o12,o13,o14,o51,o52,o131;
wire [31:0] b15,o15;

assign a1 = N[0]?{16'b0,M}:32'b0;   
assign a2 = N[1]?{15'b0,M,1'b0}:32'b0;   
assign a3 = N[2]?{14'b0,M,2'b0}:32'b0;   
assign a4 = N[3]?{13'b0,M,3'b0}:32'b0;   
assign a5 = N[4]?{12'b0,M,4'b0}:32'b0;   
assign a6 = N[5]?{11'b0,M,5'b0}:32'b0;   
assign a7 = N[6]?{10'b0,M,6'b0}:32'b0;   
assign a8 = N[7]?{9'b0,M,7'b0}:32'b0;
assign a9 = N[8]?{8'b0,M,8'b0}:32'b0;
assign a10 = N[9]?{7'b0,M,9'b0}:32'b0;
assign a11 = N[10]?{6'b0,M,10'b0}:32'b0;
assign a12 = N[11]?{5'b0,M,11'b0}:32'b0;
assign a13 = N[12]?{4'b0,M,12'b0}:32'b0;
assign a14 = N[13]?{3'b0,M,13'b0}:32'b0;
assign a15 = N[14]?{2'b0,M,14'b0}:32'b0;
assign a16 = N[15]?{1'b0,M,15'b0}:32'b0;

always @(posedge clk) begin
b1<=a1^ a2 ^ a3;
o1<={((a1 & a2)+(a3 & (a1 ^ a2))),1'b0};

b2<=a6 ^ a4 ^ a5;
o2<={((a6 & a4)+(a5 & (a6 ^ a4))),1'b0};

b3<=a7 ^ a8 ^ a9;
o3<={((a8 & a7)+(a9 & (a7 ^ a8))),1'b0};

b4<=a10 ^ a11 ^ a12;
o4<={((a10 & a11)+(a12 & (a10 ^ a11))),1'b0};

b5<=a13 ^ a14 ^ a15;
o5<={((a13 & a14)+(a15 & (a13 ^ a14))),1'b0};

a161<=a16;

b6<=b2 ^ b1 ^ o1;
o6<={((b1 & o1)+(b2 & (b1 ^ o1))),1'b0};

b7<=o3 ^ o2 ^ b3;
o7<={((o3 & o2)+(b3 & (o3 ^ o2))),1'b0};

b8<=b5 ^ o4 ^ b4;
o8<={((b5 & o4)+(b4 & (b5 ^ o4))),1'b0};

o51<=o5;
a162<=a161;

b10<=o6 ^ b6 ^ b7;
o10<={((o6 & b6)+(b7 & (o6 ^ b6))),1'b0};

b11<=b8 ^ o8 ^ o7;
o11<={((b8 & o8)+(o7 & (b8 ^ o8))),1'b0};

o52<=o51;
a163<=a162;

b12<=b10 ^ o10 ^ b11;
o12<={((b10 & o10)+(b11 & (b10 ^ o10))),1'b0};

b13<=o11 ^ a163 ^ o52;
o13<={((o11 & a163)+(o52 & (o11 ^ a163))),1'b0};


b14<=o12 ^ b12 ^ b13;
o14<={((o12 & b12)+(b13 & (o12 ^ b12))),1'b0};

o131<=o13;

end
assign b15=b14 ^ o14 ^ o131;
assign o15={((o14 & b14)+(o131 & (b14 ^ o14))),1'b0};

reg [31:0] D1,D2,D3,D4,D5,P1,P2,P3,P4,XO1,XO2,XO3,XO4,XO5;  
    reg [32:0] D,P; 
    always @(posedge clk) 
    begin
    P<={b15^o15,1'b0};
    D<={b15&o15,1'b0};
    end
    genvar k;
    generate
    for(k=1;k<32;k=k+1) 
	begin:FS
        always @(posedge clk) 
	begin
        D1[k]<=(D[k-1] & P[k]) + D[k];
        P1[k]<=P[k] & P[k-1];
        XO1<=P[32:1];
        end
    end
    for(k=2;k<32;k=k+1) 
	begin:SS
        always @(posedge clk) 
	begin
        D2[k]<=(D1[k-2] & P1[k]) + D1[k];
        P2[k]<=P1[k] & P1[k-2];
        XO2<=XO1;
        end
    end
    for(k=4;k<32;k=k+1) 
	begin:TS  
        always @(posedge clk) 
	begin
        D3[k]<=(D2[k-4] & P2[k]) + D2[k];
        P3[k]<=P2[k] & P2[k-4];
        XO3<=XO2;
        end
    end
    for(k=8;k<32;k=k+1) 
	begin:FFS
        always @(posedge clk) 
	begin
        D4[k]<=(D3[k-8] & P3[k]) + D3[k];
        P4[k]<=P3[k] & P3[k-8];
        XO4<=XO3;
        end
    end
    for(k=16;k<32;k=k+1) 
	begin:FFFS
    	always @(posedge clk) 
	begin
        D5[k]<=(D4[k-16] & P4[k]) + D4[k];
        XO5<=XO4;
        end
    end
    always@(posedge clk) 
    begin
    D1[0]<=D[0];

    D2[0]<=D1[0];
    D2[1]<=D1[1];
    end

    for(k=0;k<4;k=k+1)
        always @(posedge clk) D3[k]<=D2[k];

    for(k=0;k<8;k=k+1)
        always @(posedge clk) D4[k]<=D3[k]; 
        
    for(k=0;k<16;k=k+1)
    	always @(posedge clk) D5[k]<=D4[k];
    
    endgenerate

    assign O=XO5 ^ D5;
endmodule

Experiment 5- Pipelining/TestBench.v
`include "Wallace.v"
module WalMult_tb();

    reg [15:0] M,N;
    wire [31:0] O;
    reg clk;
    WalMul wm(.M(M), .N(N), .O(O), .clk(clk));
    initial begin
    $dumpfile("WalMult.vcd");
    $dumpvars(0,WalMult_tb);
    clk<=1'b0;
    M<=16'haacd;
    N<=16'hbbde;
    #2;
    M<=16'hffff;
    N<=16'hffff;
    #2;
    M<=16'hb29d;
    N<=16'hffff;
    #2;
    M<=16'h6540;
    N<=16'h3216;
    #2;
    M<=16'h3265;
    N<=16'h2656;
    #2;
    M<=16'h0000;
    N<=16'h0000;
    #2;
    M<=16'habce;
    N<=16'hbcde;
    #2;
    M<=16'hfffe;
    N<=16'hffff;
    #2;
    M<=16'hb29e;
    N<=16'hffff;
    #2;
    M<=16'h654e;
    N<=16'h3216;
    #2;
    M<=16'h326e;
    N<=16'h2656;
    #2;
    M<=16'h000e;
    N<=16'h0000;
    #10000;
    $finish;
    end
    always@(M|O)
        $display("Time: %h Input: %h %h Output:%h Clock:%b",$time,M,N,O,clk);

    always begin
    #1 clk<=1'b1;
    #1 clk<=1'b0;
    end

endmodule

Experiment 5- Pipelining/WalMult.vcd
$date
	Fri Mar  1 12:51:52 2019
$end
$version
	Icarus Verilog
$end
$timescale
	1s
$end
$scope module WalMult_tb $end
$var wire 32 ! O [31:0] $end
$var reg 16 " M [15:0] $end
$var reg 16 # N [15:0] $end
$var reg 1 $ clk $end
$scope module wm $end
$var wire 16 % M [15:0] $end
$var wire 16 & N [15:0] $end
$var wire 32 ' O [31:0] $end
$var wire 32 ( a1 [31:0] $end
$var wire 32 ) a10 [31:0] $end
$var wire 32 * a11 [31:0] $end
$var wire 32 + a12 [31:0] $end
$var wire 32 , a13 [31:0] $end
$var wire 32 - a14 [31:0] $end
$var wire 32 . a15 [31:0] $end
$var wire 32 / a16 [31:0] $end
$var wire 32 0 a2 [31:0] $end
$var wire 32 1 a3 [31:0] $end
$var wire 32 2 a4 [31:0] $end
$var wire 32 3 a5 [31:0] $end
$var wire 32 4 a6 [31:0] $end
$var wire 32 5 a7 [31:0] $end
$var wire 32 6 a8 [31:0] $end
$var wire 32 7 a9 [31:0] $end
$var wire 32 8 b15 [31:0] $end
$var wire 1 9 clk $end
$var wire 32 : o15 [31:0] $end
$var reg 33 ; D [32:0] $end
$var reg 32 < D1 [31:0] $end
$var reg 32 = D2 [31:0] $end
$var reg 32 > D3 [31:0] $end
$var reg 32 ? D4 [31:0] $end
$var reg 32 @ D5 [31:0] $end
$var reg 33 A P [32:0] $end
$var reg 32 B P1 [31:0] $end
$var reg 32 C P2 [31:0] $end
$var reg 32 D P3 [31:0] $end
$var reg 32 E P4 [31:0] $end
$var reg 32 F XO1 [31:0] $end
$var reg 32 G XO2 [31:0] $end
$var reg 32 H XO3 [31:0] $end
$var reg 32 I XO4 [31:0] $end
$var reg 32 J XO5 [31:0] $end
$var reg 32 K a161 [31:0] $end
$var reg 32 L a162 [31:0] $end
$var reg 32 M a163 [31:0] $end
$var reg 32 N b1 [31:0] $end
$var reg 32 O b10 [31:0] $end
$var reg 32 P b11 [31:0] $end
$var reg 32 Q b12 [31:0] $end
$var reg 32 R b13 [31:0] $end
$var reg 32 S b14 [31:0] $end
$var reg 32 T b2 [31:0] $end
$var reg 32 U b3 [31:0] $end
$var reg 32 V b4 [31:0] $end
$var reg 32 W b5 [31:0] $end
$var reg 32 X b6 [31:0] $end
$var reg 32 Y b7 [31:0] $end
$var reg 32 Z b8 [31:0] $end
$var reg 32 [ o1 [31:0] $end
$var reg 32 \ o10 [31:0] $end
$var reg 32 ] o11 [31:0] $end
$var reg 32 ^ o12 [31:0] $end
$var reg 32 _ o13 [31:0] $end
$var reg 32 ` o131 [31:0] $end
$var reg 32 a o14 [31:0] $end
$var reg 32 b o2 [31:0] $end
$var reg 32 c o3 [31:0] $end
$var reg 32 d o4 [31:0] $end
$var reg 32 e o5 [31:0] $end
$var reg 32 f o51 [31:0] $end
$var reg 32 g o52 [31:0] $end
$var reg 32 h o6 [31:0] $end
$var reg 32 i o7 [31:0] $end
$var reg 32 j o8 [31:0] $end
$scope begin FS[1] $end
$upscope $end
$scope begin FS[2] $end
$upscope $end
$scope begin FS[3] $end
$upscope $end
$scope begin FS[4] $end
$upscope $end
$scope begin FS[5] $end
$upscope $end
$scope begin FS[6] $end
$upscope $end
$scope begin FS[7] $end
$upscope $end
$scope begin FS[8] $end
$upscope $end
$scope begin FS[9] $end
$upscope $end
$scope begin FS[10] $end
$upscope $end
$scope begin FS[11] $end
$upscope $end
$scope begin FS[12] $end
$upscope $end
$scope begin FS[13] $end
$upscope $end
$scope begin FS[14] $end
$upscope $end
$scope begin FS[15] $end
$upscope $end
$scope begin FS[16] $end
$upscope $end
$scope begin FS[17] $end
$upscope $end
$scope begin FS[18] $end
$upscope $end
$scope begin FS[19] $end
$upscope $end
$scope begin FS[20] $end
$upscope $end
$scope begin FS[21] $end
$upscope $end
$scope begin FS[22] $end
$upscope $end
$scope begin FS[23] $end
$upscope $end
$scope begin FS[24] $end
$upscope $end
$scope begin FS[25] $end
$upscope $end
$scope begin FS[26] $end
$upscope $end
$scope begin FS[27] $end
$upscope $end
$scope begin FS[28] $end
$upscope $end
$scope begin FS[29] $end
$upscope $end
$scope begin FS[30] $end
$upscope $end
$scope begin FS[31] $end
$upscope $end
$scope begin SS[2] $end
$upscope $end
$scope begin SS[3] $end
$upscope $end
$scope begin SS[4] $end
$upscope $end
$scope begin SS[5] $end
$upscope $end
$scope begin SS[6] $end
$upscope $end
$scope begin SS[7] $end
$upscope $end
$scope begin SS[8] $end
$upscope $end
$scope begin SS[9] $end
$upscope $end
$scope begin SS[10] $end
$upscope $end
$scope begin SS[11] $end
$upscope $end
$scope begin SS[12] $end
$upscope $end
$scope begin SS[13] $end
$upscope $end
$scope begin SS[14] $end
$upscope $end
$scope begin SS[15] $end
$upscope $end
$scope begin SS[16] $end
$upscope $end
$scope begin SS[17] $end
$upscope $end
$scope begin SS[18] $end
$upscope $end
$scope begin SS[19] $end
$upscope $end
$scope begin SS[20] $end
$upscope $end
$scope begin SS[21] $end
$upscope $end
$scope begin SS[22] $end
$upscope $end
$scope begin SS[23] $end
$upscope $end
$scope begin SS[24] $end
$upscope $end
$scope begin SS[25] $end
$upscope $end
$scope begin SS[26] $end
$upscope $end
$scope begin SS[27] $end
$upscope $end
$scope begin SS[28] $end
$upscope $end
$scope begin SS[29] $end
$upscope $end
$scope begin SS[30] $end
$upscope $end
$scope begin SS[31] $end
$upscope $end
$scope begin TS[4] $end
$upscope $end
$scope begin TS[5] $end
$upscope $end
$scope begin TS[6] $end
$upscope $end
$scope begin TS[7] $end
$upscope $end
$scope begin TS[8] $end
$upscope $end
$scope begin TS[9] $end
$upscope $end
$scope begin TS[10] $end
$upscope $end
$scope begin TS[11] $end
$upscope $end
$scope begin TS[12] $end
$upscope $end
$scope begin TS[13] $end
$upscope $end
$scope begin TS[14] $end
$upscope $end
$scope begin TS[15] $end
$upscope $end
$scope begin TS[16] $end
$upscope $end
$scope begin TS[17] $end
$upscope $end
$scope begin TS[18] $end
$upscope $end
$scope begin TS[19] $end
$upscope $end
$scope begin TS[20] $end
$upscope $end
$scope begin TS[21] $end
$upscope $end
$scope begin TS[22] $end
$upscope $end
$scope begin TS[23] $end
$upscope $end
$scope begin TS[24] $end
$upscope $end
$scope begin TS[25] $end
$upscope $end
$scope begin TS[26] $end
$upscope $end
$scope begin TS[27] $end
$upscope $end
$scope begin TS[28] $end
$upscope $end
$scope begin TS[29] $end
$upscope $end
$scope begin TS[30] $end
$upscope $end
$scope begin TS[31] $end
$upscope $end
$scope begin FFS[8] $end
$upscope $end
$scope begin FFS[9] $end
$upscope $end
$scope begin FFS[10] $end
$upscope $end
$scope begin FFS[11] $end
$upscope $end
$scope begin FFS[12] $end
$upscope $end
$scope begin FFS[13] $end
$upscope $end
$scope begin FFS[14] $end
$upscope $end
$scope begin FFS[15] $end
$upscope $end
$scope begin FFS[16] $end
$upscope $end
$scope begin FFS[17] $end
$upscope $end
$scope begin FFS[18] $end
$upscope $end
$scope begin FFS[19] $end
$upscope $end
$scope begin FFS[20] $end
$upscope $end
$scope begin FFS[21] $end
$upscope $end
$scope begin FFS[22] $end
$upscope $end
$scope begin FFS[23] $end
$upscope $end
$scope begin FFS[24] $end
$upscope $end
$scope begin FFS[25] $end
$upscope $end
$scope begin FFS[26] $end
$upscope $end
$scope begin FFS[27] $end
$upscope $end
$scope begin FFS[28] $end
$upscope $end
$scope begin FFS[29] $end
$upscope $end
$scope begin FFS[30] $end
$upscope $end
$scope begin FFS[31] $end
$upscope $end
$scope begin FFFS[16] $end
$upscope $end
$scope begin FFFS[17] $end
$upscope $end
$scope begin FFFS[18] $end
$upscope $end
$scope begin FFFS[19] $end
$upscope $end
$scope begin FFFS[20] $end
$upscope $end
$scope begin FFFS[21] $end
$upscope $end
$scope begin FFFS[22] $end
$upscope $end
$scope begin FFFS[23] $end
$upscope $end
$scope begin FFFS[24] $end
$upscope $end
$scope begin FFFS[25] $end
$upscope $end
$scope begin FFFS[26] $end
$upscope $end
$scope begin FFFS[27] $end
$upscope $end
$scope begin FFFS[28] $end
$upscope $end
$scope begin FFFS[29] $end
$upscope $end
$scope begin FFFS[30] $end
$upscope $end
$scope begin FFFS[31] $end
$upscope $end
$scope begin genblk6 $end
$upscope $end
$scope begin genblk06 $end
$upscope $end
$scope begin genblk006 $end
$upscope $end
$scope begin genblk0006 $end
$upscope $end
$scope begin genblk7 $end
$upscope $end
$scope begin genblk07 $end
$upscope $end
$scope begin genblk007 $end
$upscope $end
$scope begin genblk0007 $end
$upscope $end
$scope begin genblk00007 $end
$upscope $end
$scope begin genblk000007 $end
$upscope $end
$scope begin genblk0000007 $end
$upscope $end
$scope begin genblk00000007 $end
$upscope $end
$scope begin genblk8 $end
$upscope $end
$scope begin genblk08 $end
$upscope $end
$scope begin genblk008 $end
$upscope $end
$scope begin genblk0008 $end
$upscope $end
$scope begin genblk00008 $end
$upscope $end
$scope begin genblk000008 $end
$upscope $end
$scope begin genblk0000008 $end
$upscope $end
$scope begin genblk00000008 $end
$upscope $end
$scope begin genblk000000008 $end
$upscope $end
$scope begin genblk0000000008 $end
$upscope $end
$scope begin genblk00000000008 $end
$upscope $end
$scope begin genblk000000000008 $end
$upscope $end
$scope begin genblk0000000000008 $end
$upscope $end
$scope begin genblk00000000000008 $end
$upscope $end
$scope begin genblk000000000000008 $end
$upscope $end
$scope begin genblk0000000000000008 $end
$upscope $end
$upscope $end
$upscope $end
$enddefinitions $end
#0
$dumpvars
bx j
bx i
bx h
bx g
bx f
bx e
bx d
bx c
bx b
bx a
bx `
bx _
bx ^
bx ]
bx \
bx [
bx Z
bx Y
bx X
bx W
bx V
bx U
bx T
bx S
bx R
bx Q
bx P
bx O
bx N
bx M
bx L
bx K
bx J
bx I
bx H
bx G
bx F
bx E
bx D
bx C
bx B
bx A
bx @
bx ?
bx >
bx =
bx <
bx ;
bx0 :
09
bx 8
b101010101100110100000000 7
b10101010110011010000000 6
b1010101011001101000000 5
b0 4
b10101010110011010000 3
b1010101011001101000 2
b101010101100110100 1
b10101010110011010 0
b1010101011001101000000000000000 /
b0 .
b10101010110011010000000000000 -
b1010101011001101000000000000 ,
b101010101100110100000000000 +
b0 *
b1010101011001101000000000 )
b0 (
bx '
b1011101111011110 &
b1010101011001101 %
0$
b1011101111011110 #
b1010101011001101 "
bx !
$end
#1
bx B
bx C
bx D
bx E
bx >
bx ?
bx @
bx0 a
bx0 _
bx0 ^
bx0 ]
bx0 \
bx0 j
bx0 i
bx0 h
b1010101011001101000000000000000 K
b100010000000000000000 e
b11111111101010111000000000000 W
b10101010000001000000000000 d
b100000000111111001000000000 V
b10101011100111000000000 c
b110101010001100011000000 U
b100010000000 b
b11111111101010111000 T
b1000100000 [
b111111111010101110 N
bx00 ;
bx0 A
bx =
bx <
1$
19
#2
b1111111111111111 (
b111111111111111100000 4
b11111111111111110000000000 *
b111111111111111100000000000000 .
b11111111111111110 0
b111111111111111100 1
b1111111111111111000 2
b11111111111111110000 3
b1111111111111111000000 5
b11111111111111110000000 6
b111111111111111100000000 7
b1111111111111111000000000 )
b111111111111111100000000000 +
b1111111111111111000000000000 ,
b11111111111111110000000000000 -
b1111111111111111000000000000000 /
0$
09
b1111111111111111 #
b1111111111111111 &
b1111111111111111 "
b1111111111111111 %
#3
bx0 `
b1010101011001101000000000000000 L
b100010000000000000000 f
b1101010000101110000000000000 j
b11001010111101001001000000000 Z
b101010100001000100000000 i
b100000001101111001000000 Y
b1111111010101010000 h
b11000000011000110110 X
b1111111111111111000000000000000 K
b111111111111111100000000000000 e
b101111111111111101000000000000 W
b111111111111111100000000000 d
b101111111111111101000000000 V
b111111111111111100000000 c
b101111111111111101000000 U
b111111111111111100000 b
b101111111111111101000 T
b111111111111111100 [
b101111111111111101 N
bx @
bx E
bx ?
bx D
bx >
bx C
bx =
bx0x B
bx00 <
1$
19
#4
b1011001010011101 (
b10110010100111010 0
b101100101001110100 1
b1011001010011101000 2
b10110010100111010000 3
b101100101001110100000 4
b1011001010011101000000 5
b10110010100111010000000 6
b101100101001110100000000 7
b1011001010011101000000000 )
b10110010100111010000000000 *
b101100101001110100000000000 +
b1011001010011101000000000000 ,
b10110010100111010000000000000 -
b101100101001110100000000000000 .
b1011001010011101000000000000000 /
0$
09
b1011001010011101 "
b1011001010011101 %
#5
bx0x B
bx0xxx C
bx D
bx E
bx >
bx ?
bx @
b1010101011001101000000000000000 M
b100010000000000000000 g
b10010100101010010000000000000 ]
b10100101101100110001100000000 P
b10011010110010100000 \
b100010110010110100100110 O
b1111111111111111000000000000000 L
b111111111111111100000000000000 f
b1111111111111111000000000000 j
b101101111111111101001000000000 Z
b1011111111111111010000000 i
b10111111111111110100000 Y
b1111111111111111000 h
b101101111111111101001 X
b1011001010011101000000000000000 K
b11100010001111000000000000000 e
b110001110111010011000000000000 W
b11100010001111000000000000 d
b110001110111010011000000000 V
b11100010001111000000000 c
b110001110111010011000000 U
b11100010001111000000 b
b110001110111010011000 T
b11100010001111000 [
b110001110111010011 N
bx00 =
bx00 <
1$
19
#6
b0 (
b1100101010000000 0
b11001010100000000 1
b0 2
b1100101010000000000 3
b0 4
b0 5
b0 6
b0 7
b110010101000000000000000 )
b0 *
b0 +
b110010101000000000000000000 ,
b1100101010000000000000000000 -
b0 .
b0 /
0$
09
b11001000010110 #
b11001000010110 &
b110010101000000 "
b110010101000000 %
#7
b100000001010100000000000000000 _
b1000111111000101010000000000000 R
b1000101100101101001000000 ^
b10100001101001110001010000110 Q
b1111111111111111000000000000000 M
b111111111111111100000000000000 g
b11011111111111110010000000000 ]
b100011011111111101110010000000 P
b1011111111111111010000 \
b10011101111111110110001 O
b1011001010011101000000000000000 L
b11100010001111000000000000000 f
b111001100110110000000000000 j
b110100011011100110011000000000 Z
b100011100110110110000000 i
b101110000100100100000000 Y
b111001100110110000 h
b110100011011100110011 X
b0 K
b1000000000000000000000000000 e
b1010111111000000000000000000 W
b0 d
b110010101000000000000000 V
b0 c
b0 U
b0 b
b1100101010000000000 T
b10000000000000000 [
b10101111110000000 N
bx @
bx E
bx ?
bx0xxxxxxx D
bx00 >
bx0xxx C
bx00 =
bx0x B
bx00 <
1$
19
#8
b11001001100101000000 5
b110010011001010000000000 *
b110010011001010 0
b1100100110010100 1
b110010011001010000 3
b11001001100101000000000 )
b0 ,
b110010011001010000000000000 -
0$
09
b10011001010110 #
b10011001010110 &
b11001001100101 "
b11001001100101 %
#9
b100110100000000000000000000 :
b1111000100001111101110011000110 8
bx0x B
bx0xxx C
bx0xxxxxxx D
bx0xxxxxxxxxxxxxxx E
bx00 >
bx00 ?
bx @
b100000001010100000000000000000 `
b1010011011011100010000000000 a
b1010010110000000001100011000110 S
b1111111111111111000000000000000 _
b1011011111111111010010000000000 R
b110111111111111100100000 ^
b100011000111101101110011100001 Q
b1011001010011101000000000000000 M
b11100010001111000000000000000 g
b1000010111001100100000000000 ]
b110011110100110110101110000000 P
b1101000011001001100000 \
b101000011110011110000011 O
b0 L
b1000000000000000000000000000 f
b1100100000000000000000000 j
b1010001101101000000000000000 Z
b0 i
b0 Y
b101010100000000000 h
b1100000101110000000 X
b0 e
b110010011001010000000000000 W
b100000010000000000000000 d
b101011010101111000000000 V
b11001001100101000000 U
b110010011001010000 T
b1000000100000000 [
b1010110101011110 N
bx00 =
bx00 <
1$
19
#10
b0 0
b0 1
b0 3
b0 5
b0 )
b0 *
b0 -
0$
09
b0 #
b0 &
b0 "
b0 %
#11
b11111111011111110000000010000000 :
b11111101111111110000001 8
b1000000000000000000000000 ;
b11111000101011111011100110001100 A
b1111111111111111000000000000000 `
b111101111111111100001000000 a
b1111000001111101000011111000001 S
b110000100111010000000000000000 _
b1001101010101011100100000000000 R
b1011000101100011100000000 ^
b110011010001101011111001100011 Q
b0 M
b1000000000000000000000000000 g
b1000000000000000000000 ]
b1011101001101000000000000000 P
b1000001000000000000 \
b1001010001110000000 O
b0 f
b1000110100000000000000000 j
b110011000001111111000000000 Z
b11001001100101000000 Y
b10100101010100000 h
b110000101000001110 X
b0 W
b0 d
b0 V
b0 U
b0 T
b0 [
b0 N
bx00 @
bx0xxxxxxxxxxxxxxx E
bx00 ?
bx0xxxxxxx D
bx00 >
bx0xxx C
bx00 =
bx0x B
bx00 <
1$
19
#12
b10101011110011100 0
b101010111100111000 1
b1010101111001110000 2
b10101011110011100000 3
b1010101111001110000000 5
b10101011110011100000000 6
b10101011110011100000000000 *
b101010111100111000000000000 +
b1010101111001110000000000000 ,
b10101011110011100000000000000 -
b1010101111001110000000000000000 /
0$
09
b1011110011011110 #
b1011110011011110 &
b1010101111001110 "
b1010101111001110 %
#13
b1100101001110110010000000000000 :
b1001101011000010010110101100011 8
b1111100010101111101110011000110 F
b1111000000001111001100010000100x B
bx0xxx C
bx0xxxxxxx D
bx0xxxxxxxxxxxxxxx E
bx00 >
bx00 ?
bx00 @
b110000100111010000000000000000 `
b10100011011001110000000000 a
b1111111011100011011000101100011 S
b0 _
b1000001000000000000000000000 R
b10010000000000000000 ^
b1011101001100011001110000000 Q
b0 g
b0 ]
b111011110101111111000000000 P
b100001010000000000 \
b11101101100111101110 O
b0 j
b0 Z
b0 Y
b0 h
b0 X
b1010101111001110000000000000000 K
b11100011000000000000000 e
b11111110001010010000000000000 W
b111000110000000000000 d
b111111100010100100000000000 V
b11100011000000000 c
b11111110001010010000000 U
b11100011000000 b
b11111110001010010000 T
b111000110000 [
b111111100010100100 N
b111111000000000100000000 ;
b111111110000000111111111000000010 A
bx00 =
b1000000000000000000000000 <
1$
19
#14
b1111111111111110 (
b111111111111111000000 4
b111111111111111000000000 7
b1111111111111110000000000 )
b111111111111111000000000000000 .
b11111111111111100 0
b111111111111111000 1
b1111111111111110000 2
b11111111111111100000 3
b1111111111111110000000 5
b11111111111111100000000 6
b11111111111111100000000000 *
b111111111111111000000000000 +
b1111111111111110000000000000 ,
b11111111111111100000000000000 -
b1111111111111110000000000000000 /
0$
09
b1111111111111111 #
b1111111111111111 &
b1111111111111110 "
b1111111111111110 %
#15
b0 :
b10011110011110011001110000000 8
b10001010010000100100000000000000 ;
b1010000101101000001101011000110 A
b0 `
b10000010000000000000000000000 a
b11100011110011001110000000 S
b0 R
b101011011100000000000 ^
b111011101100011001111101110 Q
b0 P
b0 \
b0 O
b1010101111001110000000000000000 L
b11100011000000000000000 f
b1111101010101100000000000000 j
b11000001010000000100000000000 Z
b100010100100000000 i
b11111101110101001000000 Y
b1111101010101100000 h
b11000001010000000100 X
b1111111111111110000000000000000 K
b111111111111111000000000000000 e
b101111111111111010000000000000 W
b111111111111111000000000000 d
b101111111111111010000000000 V
b111111111111111000000000 c
b101111111111111010000000 U
b111111111111111000000 b
b101111111111111010000 T
b111111111111111000 [
b101111111111111010 N
bx00 @
bx0xxxxxxxxxxxxxxx E
bx00 ?
bx0xxxxxxx D
bx00 >
b1111100010101111101110011000110 G
b110000000000110000000000000000xx C
b1000000000000000000000000 =
b11111111000000011111111100000001 F
b1111110000000011111111000000000x B
b111111000000001100000000 <
1$
19
#16
b1011001010011110 (
b10110010100111100 0
b101100101001111000 1
b1011001010011110000 2
b10110010100111100000 3
b101100101001111000000 4
b1011001010011110000000 5
b10110010100111100000000 6
b101100101001111000000000 7
b1011001010011110000000000 )
b10110010100111100000000000 *
b101100101001111000000000000 +
b1011001010011110000000000000 ,
b10110010100111100000000000000 -
b101100101001111000000000000000 .
b1011001010011110000000000000000 /
0$
09
b1011001010011110 "
b1011001010011110 %
#17
b10000000000000000000000 :
b111010010111110101111101110 8
b101000010110100000110101100011 F
b100000000100001000010x B
b11111111000000011111111100000001 G
b111100000000001111110000000000xx C
b1111100010101111101110011000110 H
b0xxxx D
bx0xxxxxxxxxxxxxxx E
b1000000000000000000000000 >
bx00 ?
bx00 @
b1010000110000000000000 a
b111011000111000101111101110 S
b0 ^
b0 Q
b1010101111001110000000000000000 M
b11100011000000000000000 g
b10000010101000001000000000000 ]
b10111100000001110000100000000 P
b111011010100010000000 \
b11101010010101100100100 O
b1111111111111110000000000000000 L
b111111111111111000000000000000 f
b1111111111111110000000000000 j
b101101111111111010010000000000 Z
b1011111111111110100000000 i
b10111111111111101000000 Y
b1111111111111110000 h
b101101111111111010010 X
b1011001010011110000000000000000 K
b11100010001111000000000000000 e
b110001110111011010000000000000 W
b11100010001111000000000000 d
b110001110111011010000000000 V
b11100010001111000000000 c
b110001110111011010000000 U
b11100010001111000000 b
b110001110111011010000 T
b11100010001111000 [
b110001110111011010 N
b0 ;
b100111100111100110011100000000 A
b111111000000111100000000 =
b10011010110001100100000000000000 <
1$
19
#18
b0 (
b1100101010011100 0
b11001010100111000 1
b0 2
b1100101010011100000 3
b0 4
b0 5
b0 6
b0 7
b110010101001110000000000 )
b0 *
b0 +
b110010101001110000000000000 ,
b1100101010011100000000000000 -
b0 .
b0 /
0$
09
b11001000010110 #
b11001000010110 &
b110010101001110 "
b110010101001110 %
#19
b0 :
b0 8
b100000000000000000000000 ;
b1110000101111101011111011100 A
b0 a
b0 S
b100000111010100000000000000000 _
b1000101110000101001000000000000 R
b1010110101001000000000 ^
b10111111010000110001010100100 Q
b1111111111111110000000000000000 M
b111111111111111000000000000000 g
b11011111111111100100000000000 ]
b100011011111111011100100000000 P
b1011111111111110100000 \
b10011101111111101100010 O
b1011001010011110000000000000000 L
b11100010001111000000000000000 f
b111001100110110000000000000 j
b110100011011101110010000000000 Z
b100011100110110100000000 i
b101110000100101101000000 Y
b111001100110110000 h
b110100011011101110010 X
b0 K
b1000000000011000000000000000 e
b1010111111010010000000000000 W
b0 d
b110010101001110000000000 V
b0 c
b0 U
b0 b
b1100101010011100000 T
b10000000000110000 [
b10101111110100100 N
bx00 @
b1111100010101111101110011000110 I
b0xxxxxxxx E
b1000000000000000000000000 ?
b11111111000000011111111100000001 H
b11000000000000xxxx D
b111111001111111100000000 >
b101000010110100000110101100011 G
b0xxx C
b10011010110001100100000000000000 =
b10011110011110011001110000000 F
b11100011100010001100000000x B
b0 <
1$
19
#20
b11001001101110000000 5
b110010011011100000000000 *
b110010011011100 0
b1100100110111000 1
b110010011011100000 3
b11001001101110000000000 )
b0 ,
b110010011011100000000000000 -
0$
09
b10011001010110 #
b10011001010110 &
b11001001101110 "
b11001001101110 %
#21
b101100000010100000000000000 :
b1111101010101111101110011000110 !
b1111101010101111101110011000110 '
b1111001001111110000010010100100 8
b111000010111110101111101110 F
b110000000111100001111001100x B
b10011110011110011001110000000 G
b1000001000000000000000000xx C
b101000010110100000110101100011 H
b0xxxx D
b11111111000000011111111100000001 I
b0xxxxxxxx E
b1111100010101111101110011000110 J
b10011010110001100100000000000000 >
b111111111111111100000000 ?
b1000000000000000000000000 @
b100000111010100000000000000000 `
b1011110101001010010000000000 a
b1010010000000011010000010100100 S
b1111111111111110000000000000000 _
b1011011111111110100100000000000 R
b110111111111111001000000 ^
b100011000111101011100111000010 Q
b1011001010011110000000000000000 M
b11100010001111000000000000000 g
b1000010111001100100000000000 ]
b110011110100111110100100000000 P
b1101000011011011100000 \
b101000011110010110000010 O
b0 L
b1000000000011000000000000000 f
b1100100000000000000000000 j
b1010001101111011110000000000 Z
b0 i
b0 Y
b101010100101000000 h
b1100000101101110100 X
b0 e
b110010011011100000000000000 W
b100000010011000000000000 d
b101011010110010000000000 V
b11001001101110000000 U
b110010011011100000 T
b1000000100110000 [
b1010110101100100 N
b0 ;
b0 A
b0 =
b100000000000000000000000 <
1$
19
#22
b0 0
b0 1
b0 3
b0 5
b0 )
b0 *
b0 -
0$
09
b0 #
b0 &
b1110 "
b1110 %
