Experiment 6- Instruction Fetch Unit/IFU.v
module IFU(input wire [15:0] Ini_Value, input wire clk, input wire rst, output wire [15:0] instruct);
reg [15:0] PC;
reg [15:0] I_Mem[0:1023];
always @(rst) begin
    PC = Ini_Value;
    I_Mem[0] = 16'h0001;
    I_Mem[1] = 16'h0002;
    I_Mem[2] = 16'h0003;
    I_Mem[3] = 16'h0004;
    I_Mem[4] = 16'h0005;
    I_Mem[5] = 16'h0000;

end
always @(posedge clk & ~rst) 
begin
    PC <= PC + 1'b1;
end
    assign instruct = I_Mem[PC & 10'h3ff];

endmodule

Experiment 6- Instruction Fetch Unit/TestBench.v
`include "IFU.v"
module IFU_tb();
    reg [15:0] I, O;
    wire [15:0] instruct;
    reg clk, rst;
    IFU unit(I, clk, rst, instruct);
    initial begin
    $dumpfile("IFU.vcd");
    $dumpvars(0,IFU_tb);
    clk <= 1'b0;
    I <= 16'h0003;
    rst <= 1'b1;
    #5;
    rst <= 1'b0;
    #100;
    $finish;
    end
    always begin
    #1 clk <= 1'b1;
    O <= instruct;
    #1 clk <= 1'b0;
    end
    always @(O|rst) $display("Input : %h Output : %h Clock : %b Reset : %b",I,O,clk,rst);
endmodule

Experiment 6- Instruction Fetch Unit/IFU.vcd
$date
	Fri Mar  1 13:08:05 2019
$end
$version
	Icarus Verilog
$end
$timescale
	1s
$end
$scope module IFU_tb $end
$var wire 16 ! instruct [15:0] $end
$var reg 16 " I [15:0] $end
$var reg 16 # O [15:0] $end
$var reg 1 $ clk $end
$var reg 1 % rst $end
$scope module unit $end
$var wire 16 & Ini_Value [15:0] $end
$var wire 1 ' clk $end
$var wire 16 ( instruct [15:0] $end
$var wire 1 ) rst $end
$var reg 16 * PC [15:0] $end
$upscope $end
$upscope $end
$enddefinitions $end
#0
$dumpvars
b11 *
1)
b100 (
0'
b11 &
1%
0$
bx #
b11 "
b100 !
$end
#1
b100 #
1$
1'
#2
0$
0'
#3
1$
1'
#4
0$
0'
#5
b101 !
b101 (
b100 *
1$
1'
0%
0)
#6
0$
0'
#7
b0 !
b0 (
b101 *
b101 #
1$
1'
#8
0$
0'
#9
bx !
bx (
b110 *
b0 #
1$
1'
#10
0$
0'
#11
b111 *
bx #
1$
1'
#12
0$
0'
#13
b1000 *
1$
1'
#14
0$
0'
#15
b1001 *
1$
1'
#16
0$
0'
#17
b1010 *
1$
1'
#18
0$
0'
#19
b1011 *
1$
1'
#20
0$
0'
#21
b1100 *
1$
1'
#22
0$
0'
#23
b1101 *
1$
1'
#24
0$
0'
#25
b1110 *
1$
1'
#26
0$
0'
#27
b1111 *
1$
1'
#28
0$
0'
#29
b10000 *
1$
1'
#30
0$
0'
#31
b10001 *
1$
1'
#32
0$
0'
#33
b10010 *
1$
1'
#34
0$
0'
#35
b10011 *
1$
1'
#36
0$
0'
#37
b10100 *
1$
1'
#38
0$
0'
#39
b10101 *
1$
1'
#40
0$
0'
#41
b10110 *
1$
1'
#42
0$
0'
#43
b10111 *
1$
1'
#44
0$
0'
#45
b11000 *
1$
1'
#46
0$
0'
#47
b11001 *
1$
1'
#48
0$
0'
#49
b11010 *
1$
1'
#50
0$
0'
#51
b11011 *
1$
1'
#52
0$
0'
#53
b11100 *
1$
1'
#54
0$
0'
#55
b11101 *
1$
1'
#56
0$
0'
#57
b11110 *
1$
1'
#58
0$
0'
#59
b11111 *
1$
1'
#60
0$
0'
#61
b100000 *
1$
1'
#62
0$
0'
#63
b100001 *
1$
1'
#64
0$
0'
#65
b100010 *
1$
1'
#66
0$
0'
#67
b100011 *
1$
1'
#68
0$
0'
#69
b100100 *
1$
1'
#70
0$
0'
#71
b100101 *
1$
1'
#72
0$
0'
#73
b100110 *
1$
1'
#74
0$
0'
#75
b100111 *
1$
1'
#76
0$
0'
#77
b101000 *
1$
1'
#78
0$
0'
#79
b101001 *
1$
1'
#80
0$
0'
#81
b101010 *
1$
1'
#82
0$
0'
#83
b101011 *
1$
1'
#84
0$
0'
#85
b101100 *
1$
1'
#86
0$
0'
#87
b101101 *
1$
1'
#88
0$
0'
#89
b101110 *
1$
1'
#90
0$
0'
#91
b101111 *
1$
1'
#92
0$
0'
#93
b110000 *
1$
1'
#94
0$
0'
#95
b110001 *
1$
1'
#96
0$
0'
#97
b110010 *
1$
1'
#98
0$
0'
#99
b110011 *
1$
1'
#100
0$
0'
#101
b110100 *
1$
1'
#102
0$
0'
#103
b110101 *
1$
1'
#104
0$
0'
#105
b110110 *
1$
1'
